pdf_text_digitizer/__init__.py
pdf_text_digitizer/config.py
pdf_text_digitizer/digitize.py
pdf_text_digitizer/pdf_reader.py
pdf_text_digitizer/utils.py
tests/__init__.py
tests/test_digitize.py
tests/test_pdf_reader.py
tests/test_utils.py
pdf_text_digitizer-0.1.0.dist-info/LICENSE
pdf_text_digitizer-0.1.0.dist-info/METADATA
pdf_text_digitizer-0.1.0.dist-info/WHEEL
pdf_text_digitizer-0.1.0.dist-info/entry_points.txt
pdf_text_digitizer-0.1.0.dist-info/top_level.txt
pdf_text_digitizer-0.1.0.dist-info/RECORD
