Metadata-Version: 2.1
Name: pdf-text-digitizer
Version: 0.1.0
Summary: A package for digitizing text from PDF files.
Home-page: https://github.com/rohitium/pdf_text_digitizer
Author: Rohit Satija
Author-email: rohitsatija0092@gmail.com
License: UNKNOWN
Platform: UNKNOWN
Classifier: Programming Language :: Python :: 3
Classifier: License :: OSI Approved :: MIT License
Classifier: Operating System :: OS Independent
Requires-Python: >=3.6
License-File: LICENSE
Requires-Dist: PyPDF2
Requires-Dist: pytesseract
Requires-Dist: Pillow
Requires-Dist: pdf2image
